{
  "data": [ 
    {
      "no":          "00001",
      "account":     "stu01",
      "Cname":       "張花一",
      "Ename":       "",
      "grade":       "1",
      "class":       "Test 01",
      "onlineCount": "10",
      "usageTime":   "305小時 52分 30秒"
    },
	{
      "no":          "00002",
      "account":     "stu02",
      "Cname":       "陳二二",
      "Ename":       "",
      "grade":       "5",
      "class":       "Test 01",
      "onlineCount": "10",
      "usageTime":   "295小時 52分 30秒"
    },  
    {
      "no":          "00003",
      "account":     "stu03",
      "Cname":       "張三三",
      "Ename":       "",
      "grade":       "2",
      "class":       "Test 01",
      "onlineCount": "10",
      "usageTime":   "300小時 53分 30秒"
    },
	{
      "no":          "00004",
      "account":     "stu04",
      "Cname":       "劉玲玲",
      "Ename":       "",
      "grade":       "1",
      "class":       "Test 01",
      "onlineCount": "5",
      "usageTime":   "300小時 52分 20秒"
    },
	{
      "no":          "00005",
      "account":     "stu05",
      "Cname":       "吳五五",
      "Ename":       "",
      "grade":       "2",
      "class":       "Test 01",
      "onlineCount": "20",
      "usageTime":   "300小時 52分 00秒"
    }
	  
  ]
}